{"stats":{"minecraft:mined":{"twilightforest:firefly":5,"luminousworld:groundpebbles_1":3,"luminousworld:grassvariant_4":2,"twilightforest:hedge":1,"minecraft:dandelion":1,"minecraft:grass_block":6,"luminousworld:grassvariant_2":2,"luminousworld:grassflowers":4,"minecraft:tall_grass":2,"minecraft:spruce_leaves":1,"twilightforest:mayapple":1,"luminousworld:groundpebbles_3":1,"twilightforest:fallen_leaves":1,"twilightforest:mushgloom":2,"twilightforest:twilight_oak_leaves":2,"minecraft:grass":71,"twilightforest:cicada_jar":2,"minecraft:potatoes":1,"minecraft:vine":2,"minecraft:dirt":4,"luminousworld:decorative_brown_2":1,"minecraft:oak_leaves":15},"minecraft:custom":{"minecraft:mob_kills":8,"minecraft:time_since_death":54177,"minecraft:sleep_in_bed":1,"minecraft:climb_one_cm":8921,"minecraft:time_since_rest":37718,"minecraft:sprint_one_cm":186162,"minecraft:damage_taken":894,"minecraft:walk_one_cm":271847,"minecraft:drop":25,"minecraft:damage_dealt":1190,"minecraft:swim_one_cm":7274,"minecraft:fly_one_cm":4468496,"minecraft:open_chest":5,"minecraft:crouch_one_cm":565,"minecraft:play_time":54177,"tombstone:undead_killed":3,"minecraft:sneak_time":192,"minecraft:walk_under_water_one_cm":23572,"minecraft:jump":1334,"minecraft:walk_on_water_one_cm":38384,"minecraft:total_world_time":54177,"minecraft:fall_one_cm":19138},"minecraft:dropped":{"minecraft:bread":1,"minecraft:wheat_seeds":16,"alexsmobs:animal_dictionary":1,"minecraft:diamond":1,"tombstone:grave_dust":5,"minecraft:arrow":1},"minecraft:picked_up":{"twilightforest:cicada_jar":2,"luminousworld:groundpebbles_1":4,"minecraft:allium":1,"minecraft:feather":2,"luminousworld:decorative_brown_2":1,"minecraft:chicken":1,"minecraft:leather":1,"minecraft:potato":3,"minecraft:dirt":27,"minecraft:string":4,"minecraft:iron_axe":1,"minecraft:smooth_stone_slab":1,"minecraft:iron_leggings":1,"minecraft:bone":3,"minecraft:apple":1,"minecraft:wheat_seeds":31,"minecraft:gold_nugget":1,"minecraft:written_book":1,"twilightforest:cracked_nagastone_stairs_right":2,"twilightforest:mushgloom":4,"minecraft:stone_brick_slab":1,"minecraft:dandelion":1,"tombstone:grave_dust":6,"twilightforest:firefly":5,"twilightforest:mossy_etched_nagastone":1,"minecraft:polished_andesite":1,"luminousworld:grassflowers":5,"minecraft:arrow":1,"minecraft:diamond":1,"twilightforest:etched_nagastone":3,"minecraft:bread":27,"minecraft:oak_sapling":1},"minecraft:killed":{"minecraft:spider":1,"twilightforest:kobold":1,"twilightforest:skeleton_druid":1,"minecraft:skeleton":2,"twilightforest:naga":1,"twilightforest:swarm_spider":1,"minecraft:chicken":1},"minecraft:used":{"luminousworld:groundpebbles_1":4,"luminousworld:decorative_brown_2":1,"minecraft:dirt":27,"twilightforest:cicada_jar":2,"luminousworld:grassflowers":5,"minecraft:allium":1,"minecraft:apple":1,"twilightforest:firefly":1,"minecraft:iron_axe":106,"minecraft:bread":24,"twilightforest:mushgloom":1,"minecraft:oak_sapling":1,"minecraft:potato":6}},"DataVersion":3465}